{
	"playlist" : [{
		"name" : "90s",
		"list": [{
				"imgsrc" : "assets/images/jamiexx.jpg",
				"filessrc" : "assets/files/jamiexx-gosh.mp3",
				"singer" : "Jamie XX",
				"title" : "Gosh"
			 },
			 {
				"imgsrc" : "assets/images/jamiexx.jpg",
				"filessrc" : "assets/files/jamiexx-gosh.mp3",
				"singer" : "Jamie XX",
				"title" : "Gosh2"
			 },
			 {
				"imgsrc" : "assets/images/jamiexx.jpg",
				"filessrc" : "assets/files/jamiexx-gosh.mp3",
				"singer" : "Jamie XX",
				"title" : "Gosh3"
			},
			{
			   "imgsrc" : "assets/images/jamiexx.jpg",
			   "filessrc" : "assets/files/jamiexx-gosh.mp3",
			   "singer" : "Jamie XX",
			   "title" : "Gosh4"
			},
			{
			   "imgsrc" : "assets/images/jamiexx.jpg",
			   "filessrc" : "assets/files/jamiexx-gosh.mp3",
			   "singer" : "Jamie XX",
			   "title" : "Gosh5"
			}]
		},{
		"name": "Vive el verano",
		"list": [{
				"imgsrc" : "assets/images/jamiexx.jpg",
				"filessrc" : "assets/files/jamiexx-gosh.mp3",
				"singer" : "Jamie XX",
				"title" : "Gosh"
			 },
			 {
				"imgsrc" : "assets/images/jamiexx.jpg",
				"filessrc" : "assets/files/jamiexx-gosh.mp3",
				"singer" : "Jamie XX",
				"title" : "Gosh2"
			 },
			 {
				"imgsrc" : "assets/images/jamiexx.jpg",
				"filessrc" : "assets/files/jamiexx-gosh.mp3",
				"singer" : "Jamie XX",
				"title" : "Gosh3"
			},
			{
			   "imgsrc" : "assets/images/jamiexx.jpg",
			   "filessrc" : "assets/files/jamiexx-gosh.mp3",
			   "singer" : "Jamie XX",
			   "title" : "Gosh4"
			},
			{
			   "imgsrc" : "assets/images/jamiexx.jpg",
			   "filessrc" : "assets/files/jamiexx-gosh.mp3",
			   "singer" : "Jamie XX",
			   "title" : "Gosh5"
			}]
		}]
}
